iceberg_evolve/__init__.py
iceberg_evolve/catalog.py
iceberg_evolve/cli.py
iceberg_evolve/diff.py
iceberg_evolve/exceptions.py
iceberg_evolve/migrate.py
iceberg_evolve/renderer.py
iceberg_evolve/schema.py
iceberg_evolve/serializer/__init__.py
iceberg_evolve/serializer/json_serializer.py
iceberg_evolve/utils.py
iceberg_evolve-1.0.1.dist-info/LICENSE
iceberg_evolve-1.0.1.dist-info/METADATA
iceberg_evolve-1.0.1.dist-info/WHEEL
iceberg_evolve-1.0.1.dist-info/entry_points.txt
iceberg_evolve-1.0.1.dist-info/RECORD
