Metadata-Version: 2.3
Name: iceberg-evolve
Version: 1.0.1
Summary: Schema diffing and evolution tool for Iceberg and beyond.
Keywords: iceberg,schema,evolution,data-engineering
Author: Anatol Jurenkow
Author-email: azurius@t-online.de
Requires-Python: >=3.10
Classifier: License :: OSI Approved :: MIT License
Classifier: Programming Language :: Python :: 3.10
Classifier: Programming Language :: Python :: 3.11
Classifier: Programming Language :: Python :: 3.12
Classifier: Intended Audience :: Developers
Classifier: Topic :: Software Development :: Libraries :: Python Modules
Provides-Extra: dev
Requires-Dist: boto3 (>=1.34.0,<2.0.0)
Requires-Dist: moto (>=5.1.1,<6.0.0) ; extra == "dev"
Requires-Dist: pyiceberg[hive,pyarrow] (>=0.9.1,<1.0.0)
Requires-Dist: pytest (>=8.3.5,<9.0.0) ; extra == "dev"
Requires-Dist: pytest-cov (>=6.0.0,<7.0.0) ; extra == "dev"
Requires-Dist: pytest-mock (>=3.14.0,<4.0.0) ; extra == "dev"
Requires-Dist: rich (>=10.11.0,<14.0.0)
Requires-Dist: ruff (>=0.9.9,<1.0.0) ; extra == "dev"
Requires-Dist: schemaworks (>=1.1.0,<2.0.0)
Requires-Dist: typer (>=0.16.0,<0.17.0)
Project-URL: Homepage, https://github.com/anatol-ju/iceberg-evolve
Project-URL: Repository, https://github.com/anatol-ju/iceberg-evolve
